pbs_exporter/__init__.py
pbs_exporter/exporter.py
pbs_exporter/pbs_client.py
pbs_exporter-0.2.1.dist-info/METADATA
pbs_exporter-0.2.1.dist-info/WHEEL
pbs_exporter-0.2.1.dist-info/entry_points.txt
pbs_exporter-0.2.1.dist-info/top_level.txt
pbs_exporter-0.2.1.dist-info/RECORD
